classification_model/VERSION
classification_model/__init__.py
classification_model/config.yml
classification_model/pipeline.py
classification_model/predict.py
classification_model/train_pipeline.py
classification_model/config/__init__.py
classification_model/config/core.py
classification_model/preprocessing/__init__.py
classification_model/preprocessing/data_manager.py
classification_model/preprocessing/features.py
classification_model/preprocessing/validation.py
classification_model/trained_models/titanic_classification_model_output_v1.5.0.joblib
tid_titanic_classification_model-1.5.0.dist-info/METADATA
tid_titanic_classification_model-1.5.0.dist-info/WHEEL
tid_titanic_classification_model-1.5.0.dist-info/top_level.txt
tid_titanic_classification_model-1.5.0.dist-info/RECORD
